distributed/__init__.py
distributed/task.py
tf_yarn/__init__.py
tf_yarn/_criteo.py
tf_yarn/_env.py
tf_yarn/_internal.py
tf_yarn/_task_commons.py
tf_yarn/client.py
tf_yarn/constants.py
tf_yarn/default.log.conf
tf_yarn/evaluator_metrics.py
tf_yarn/event.py
tf_yarn/metrics.py
tf_yarn/mlflow.py
tf_yarn/packaging.py
tf_yarn/tensorboard.py
tf_yarn/topologies.py
tf_yarn/bin/__init__.py
tf_yarn/bin/check_hadoop_env.py
tf_yarn/distributed/__init__.py
tf_yarn/distributed/client.py
tf_yarn/distributed/task.py
tf_yarn/examples/__init__.py
tf_yarn/examples/collective_all_reduce_example.py
tf_yarn/examples/id_estimator_example.py
tf_yarn/examples/keras_example.py
tf_yarn/examples/linear_classifier_example.py
tf_yarn/examples/mlflow_example.py
tf_yarn/examples/native_keras_with_gloo_example.py
tf_yarn/examples/winequality.py
tf_yarn/examples/pytorch/__init__.py
tf_yarn/examples/pytorch/pytorch_distributed_example.py
tf_yarn/examples/pytorch/pytorch_example.py
tf_yarn/pytorch/__init__.py
tf_yarn/pytorch/client.py
tf_yarn/pytorch/experiment.py
tf_yarn/pytorch/model_ckpt.py
tf_yarn/pytorch/parquet_dataset.py
tf_yarn/pytorch/tasks/__init__.py
tf_yarn/pytorch/tasks/worker.py
tf_yarn/tensorflow/__init__.py
tf_yarn/tensorflow/client.py
tf_yarn/tensorflow/cluster.py
tf_yarn/tensorflow/experiment.py
tf_yarn/tensorflow/keras_experiment.py
tf_yarn/tensorflow/metrics.py
tf_yarn/tensorflow/tasks/__init__.py
tf_yarn/tensorflow/tasks/_independent_workers_task.py
tf_yarn/tensorflow/tasks/_tensorboard_task.py
tf_yarn/tensorflow/tasks/evaluator_task.py
tf_yarn/tensorflow/tasks/gloo_allred_task.py
tf_yarn/tensorflow/tasks/tf_task_common.py
tf_yarn-0.7.0.dist-info/LICENSE
tf_yarn-0.7.0.dist-info/METADATA
tf_yarn-0.7.0.dist-info/WHEEL
tf_yarn-0.7.0.dist-info/entry_points.txt
tf_yarn-0.7.0.dist-info/top_level.txt
tf_yarn-0.7.0.dist-info/RECORD
