Metadata-Version: 2.1
Name: tf-yarn
Version: 0.7.0
Summary: Distributed TensorFlow or pythorch on a YARN cluster
Home-page: https://github.com/criteo/tf-yarn
Maintainer: Criteo
Maintainer-email: github@criteo.com
License: UNKNOWN
Keywords: tensorflow pytorch yarn
Platform: UNKNOWN
Classifier: Development Status :: 4 - Beta
Classifier: Intended Audience :: Developers
Classifier: Intended Audience :: Science/Research
Classifier: Operating System :: POSIX :: Linux
Classifier: Environment :: Console
Classifier: License :: OSI Approved :: Apache Software License
Classifier: Programming Language :: Python :: 3
Classifier: Programming Language :: Python :: 3.7
Classifier: Programming Language :: Python :: 3.8
Classifier: Programming Language :: Python :: 3.9
Classifier: Topic :: Software Development :: Libraries
Requires-Python: >=3.7
License-File: LICENSE
Requires-Dist: cluster-pack <3.0.0,>=0.2.19
Requires-Dist: skein <0.9,>=0.8
Requires-Dist: tensorboard
Requires-Dist: tensorflow-io
Requires-Dist: pyarrow
Requires-Dist: psutil
Provides-Extra: cpu
Requires-Dist: tensorflow-io[tensorflow] >=0.8.0 ; extra == 'cpu'
Provides-Extra: gpu
Requires-Dist: tensorflow-io[tensorflow] >=0.8.0 ; extra == 'gpu'
